playwright_request/__init__.py
playwright_request/browser_type.py
playwright_request/error_page_detector.py
playwright_request/playwright_get.py
playwright_request/playwright_request.py
playwright_request/playwright_response.py
playwright_request/route_interceptor.py
playwright_request/commom_error_page_detectors/__init__.py
playwright_request/commom_error_page_detectors/airbnb_error_page_detector.py
playwright_request/commom_error_page_detectors/amazon_error_page_detector.py
playwright_request/commom_error_page_detectors/proxy_error_page_detector.py
playwright_request/commom_error_page_detectors/tripadvisor_error_page_detector.py
playwright_request/commom_error_page_detectors/templates/airbnb_error_page_template.yml
playwright_request/commom_error_page_detectors/templates/amazon_error_page_template.yml
playwright_request/commom_error_page_detectors/templates/proxy_error_page_template.yml
playwright_request/commom_error_page_detectors/templates/tripadvisor_error_page_template.yml
playwright_request/utils/__init__.py
playwright_request/utils/log_message.py
playwright_request-1.5.0.dist-info/LICENSE
playwright_request-1.5.0.dist-info/METADATA
playwright_request-1.5.0.dist-info/WHEEL
playwright_request-1.5.0.dist-info/top_level.txt
playwright_request-1.5.0.dist-info/RECORD
